nepali_address_system/__init__.py
nepali_address_system/addresses.py
nepali_address_system/data.py
nepali_address_system/districts.py
nepali_address_system/municipalities.py
nepali_address_system/provinces.py
nepali_address_system-0.0.3.dist-info/LICENSE
nepali_address_system-0.0.3.dist-info/METADATA
nepali_address_system-0.0.3.dist-info/WHEEL
nepali_address_system-0.0.3.dist-info/top_level.txt
nepali_address_system-0.0.3.dist-info/RECORD
